ansible_review-0.9.0.data/scripts/ansible-review
ansible_review-0.9.0.dist-info/DESCRIPTION.rst
ansible_review-0.9.0.dist-info/METADATA
ansible_review-0.9.0.dist-info/RECORD
ansible_review-0.9.0.dist-info/WHEEL
ansible_review-0.9.0.dist-info/metadata.json
ansible_review-0.9.0.dist-info/top_level.txt
ansiblereview/__init__.py
ansiblereview/code.py
ansiblereview/inventory.py
ansiblereview/playbook.py
ansiblereview/role.py
ansiblereview/vars.py
ansiblereview/version.py
ansiblereview/utils/__init__.py
ansiblereview/utils/yamlindent.py
