Metadata-Version: 2.0
Name: ansible-review
Version: 0.9.0
Summary: reviews ansible playbooks, roles and inventory and suggests improvements
Home-page: https://github.com/willthames/ansible-review
Author: Will Thames
Author-email: will@thames.id.au
License: UNKNOWN
Keywords: ansible,code review
Platform: UNKNOWN
Classifier: License :: OSI Approved :: MIT License
Requires-Dist: ansible-lint (>=3.0.0)
Requires-Dist: appdirs
Requires-Dist: pyyaml
Requires-Dist: unidiff
